gsheet_keyring.py
gsheet_keyring-1.0.1.dist-info/entry_points.txt
gsheet_keyring-1.0.1.dist-info/LICENSE
gsheet_keyring-1.0.1.dist-info/WHEEL
gsheet_keyring-1.0.1.dist-info/METADATA
gsheet_keyring-1.0.1.dist-info/RECORD
