Metadata-Version: 2.1
Name: gsheet-keyring
Version: 1.0.1
Summary: This package provides a Keyring backend that is backed by a Google Sheet.
Home-page: https://github.com/osteele/gsheet-keyring
License: UNKNOWN
Author: Oliver Steele
Author-email: steele@osteele.com
Requires-Python: >=3.5
Classifier: Intended Audience :: Developers
Classifier: License :: OSI Approved :: MIT License
Classifier: Operating System :: OS Independent
Classifier: Programming Language :: Python
Classifier: Programming Language :: Python :: 3.6
Requires-Dist: gspread
Requires-Dist: keyring
Requires-Dist: oauth2client
Project-URL: Documentation, https://gsheet-keyring.readthedocs.io/en/latest/
